j_perm/__init__.py
j_perm/engine.py
j_perm/normalizer.py
j_perm/op_handler.py
j_perm/special_resolver.py
j_perm/subst.py
j_perm/casters/__init__.py
j_perm/casters/_bool.py
j_perm/casters/_float.py
j_perm/casters/_int.py
j_perm/casters/_str.py
j_perm/constructs/__init__.py
j_perm/constructs/eval.py
j_perm/constructs/ref.py
j_perm/funcs/__init__.py
j_perm/funcs/subtract.py
j_perm/ops/__init__.py
j_perm/ops/_assert.py
j_perm/ops/_assert_d.py
j_perm/ops/_exec.py
j_perm/ops/_if.py
j_perm/ops/copy.py
j_perm/ops/copy_d.py
j_perm/ops/delete.py
j_perm/ops/distinct.py
j_perm/ops/foreach.py
j_perm/ops/replace_root.py
j_perm/ops/set.py
j_perm/ops/update.py
j_perm/schema/__init__.py
j_perm/shorthands/__init__.py
j_perm/shorthands/_assert.py
j_perm/shorthands/assign_or_append.py
j_perm/shorthands/delete.py
j_perm/utils/__init__.py
j_perm/utils/pointers.py
j_perm-0.2.1.1.dist-info/METADATA
j_perm-0.2.1.1.dist-info/WHEEL
j_perm-0.2.1.1.dist-info/top_level.txt
j_perm-0.2.1.1.dist-info/RECORD
