Metadata-Version: 2.4
Name: j-perm
Version: 0.2.1.1
Summary: json permutation library
Author-email: Roman <kuschanow@gmail.com>
License: MIT
Project-URL: Homepage, https://github.com/kuschanow/j-perm
Project-URL: Source, https://github.com/kuschanow/j-perm
Project-URL: Tracker, https://github.com/kuschanow/j-perm/issues
Requires-Python: >=3.10
Requires-Dist: jmespath
